quebec/__init__.py
quebec/logger.py
quebec/quebec.abi3.so
quebec/sqlalchemy.py
quebec-0.2.3.dist-info/METADATA
quebec-0.2.3.dist-info/WHEEL
quebec-0.2.3.dist-info/licenses/LICENSE
quebec-0.2.3.dist-info/RECORD
