Metadata-Version: 2.4
Name: quebec
Version: 0.2.3
Classifier: Programming Language :: Rust
Classifier: Programming Language :: Python :: Implementation :: CPython
Classifier: Programming Language :: Python :: Implementation :: PyPy
Classifier: Programming Language :: Python :: 3.9
Classifier: Programming Language :: Python :: 3.10
Classifier: Programming Language :: Python :: 3.11
Classifier: Programming Language :: Python :: 3.12
Classifier: Programming Language :: Python :: 3.13
Classifier: Programming Language :: Python :: 3.14
Classifier: Development Status :: 3 - Alpha
Classifier: Intended Audience :: Developers
Classifier: Topic :: Software Development :: Libraries :: Python Modules
Classifier: Operating System :: Microsoft :: Windows
Classifier: Operating System :: POSIX
Classifier: Operating System :: Unix
Classifier: Operating System :: MacOS
Requires-Dist: sphinx>=7.0 ; extra == 'docs'
Requires-Dist: shibuya ; extra == 'docs'
Requires-Dist: myst-parser ; extra == 'docs'
Requires-Dist: pytest>=7.0.0 ; extra == 'test'
Requires-Dist: pytest-cov ; extra == 'test'
Provides-Extra: docs
Provides-Extra: test
License-File: LICENSE
Summary: Quebec is a simple background task queue for processing asynchronous tasks.
Keywords: solid_queue,postgresql,mysql,sqlite,queue
Home-Page: https://github.com/ratazzi/quebec
Author-email: ratazzi <ratazzi.potts@gmail.com>
License-Expression: MIT
Requires-Python: >=3.9
Project-URL: Documentation, https://github.com/ratazzi/quebec/REDME.md
Project-URL: Homepage, https://github.com/ratazzi/quebec
Project-URL: Repository, https://github.com/ratazzi/quebec
